[
  {
    "cim": "100% Kizomba & Semba Afterwork + Kizomba Workshop",
    "datum": "2018-07-05",
    "szervezo": "Budapest Kizomba Connection - BKC",
    "idopont": "csütörtök, 19:00 – 22:00",
    "helyszin": "Barrio Latino Cafe, Budapest",
    "link": "https://www.facebook.com/events/200815220576439/",
    "kep": "/assets/images/hazai/100percent_kizomba2.jpg"
  },

  {
    "cim": "Budapest Kizomba Connection - BKC 2018",
    "datum": "2018-08-31",
    "szervezo": "Budapest Kizomba Connection - BKC",
    "idopont": "2018. augusztus 30., 21:00",
    "helyszin" :"Budapest Kizomba Connection - BKC, Budapest",
    "link":"https://www.facebook.com/events/1078373045633011/",
    "kep":"/assets/images/hazai/bkc2018.jpg"
  },

  {
    "cim": "BKC BEACH PARTY - Official Monday Afterparty",
    "datum": "2018-09-03",
    "szervezo": "Budapest Kizomba Connection - BKC",
    "idopont": "2018. szeptember 3., 14:00 – 23:00",
    "helyszin" :"Lupa Tó, Budakalász",
    "link":"https://www.facebook.com/events/517900785292351/",
    "kep":"/assets/images/hazai/lupa_to_bkc.jpg"
  }
]